icodeapi/__init__.py
icodeapi/server.py
icodeapi/tools.py
icodeapi-1.4.0.dist-info/LICENSE
icodeapi-1.4.0.dist-info/METADATA
icodeapi-1.4.0.dist-info/WHEEL
icodeapi-1.4.0.dist-info/top_level.txt
icodeapi-1.4.0.dist-info/RECORD
