Metadata-Version: 2.1
Name: icodeapi
Version: 1.4.0
Summary: The second generation of IcodeYoudao API framework.
Home-page: https://github.com/xbzstudio/icodeapi
Author: xbzstudio
Author-email: mmmhss2022@outlook.com
Project-URL: documentation, https://xbzstudio.github.io/icodeapi/docs
Classifier: Development Status :: 5 - Production/Stable
Classifier: License :: OSI Approved :: MIT License
Classifier: Programming Language :: Python :: 3.10
Classifier: Programming Language :: Python :: 3.11
Classifier: Programming Language :: Python :: 3.12
Classifier: Intended Audience :: Developers
Classifier: Topic :: Software Development :: Build Tools
Requires-Python: >=3.10
License-File: LICENSE
Requires-Dist: httpx >=0.25.0
Requires-Dist: urllib3 >=2.0.6
Requires-Dist: aiofiles >=23.2.1
